testing_helper/__init__.py
testing_helper/settings.ini
testing_helper-0.0.2.dist-info/LICENSE.txt
testing_helper-0.0.2.dist-info/METADATA
testing_helper-0.0.2.dist-info/WHEEL
testing_helper-0.0.2.dist-info/top_level.txt
testing_helper-0.0.2.dist-info/RECORD
